dockerinside/__init__.py
dockerinside/__main__.py
dockerinside/dockerutils.py
dockerinside/setup/__init__.py
dockerinside/setup/__main__.py
docker_inside-0.3.18.dist-info/LICENSE
docker_inside-0.3.18.dist-info/METADATA
docker_inside-0.3.18.dist-info/WHEEL
docker_inside-0.3.18.dist-info/entry_points.txt
docker_inside-0.3.18.dist-info/top_level.txt
docker_inside-0.3.18.dist-info/RECORD
