Metadata-Version: 2.1
Name: docker-inside
Version: 0.3.18
Summary: Run a docker container with you workspace and user
Home-page: https://github.com/boon-code/docker-inside
Author: Manuel Huber
Author-email: Manuel.h87@gmail.com
License: MIT
Classifier: Development Status :: 3 - Alpha
Classifier: License :: OSI Approved :: MIT License
Classifier: Programming Language :: Python :: 3 :: Only
Classifier: Topic :: System :: Systems Administration
License-File: LICENSE
Requires-Dist: argparse (>=1.4.0)
Requires-Dist: argcomplete (>=1.4.1)
Requires-Dist: docker (>=2.7.0)
Requires-Dist: dockerpty (>=0.4.1)
